CHANGES.rst
COPYING.txt
MANIFEST.in
README.rst
setup.cfg
setup.py
pyramid_pyctpp2/__init__.py
pyramid_pyctpp2/configure.zcml
pyramid_pyctpp2.egg-info/PKG-INFO
pyramid_pyctpp2.egg-info/SOURCES.txt
pyramid_pyctpp2.egg-info/dependency_links.txt
pyramid_pyctpp2.egg-info/not-zip-safe
pyramid_pyctpp2.egg-info/requires.txt
pyramid_pyctpp2.egg-info/top_level.txt