Metadata-Version: 1.0
Name: pyramid-pyctpp2
Version: 0.2.0
Summary: pyctpp2 template bindings for the Pyramid web framework
Home-page: http://bitbucket.org/klepa/pyramid_pyctpp2
Author: Konstantin Lepa
Author-email: konstantin.lepa@gmail.com
License: MIT
Keywords: web wsgi pylons pyramid
Platform: UNKNOWN
Classifier: Intended Audience :: Developers
Classifier: Programming Language :: Python
Classifier: Framework :: Pylons
Classifier: License :: OSI Approved :: MIT License
